{
  "unversionedId": "functions-extras/closure",
  "id": "functions-extras/closure",
  "title": "閉包 (Closure)",
  "description": "本文主要內容為探討「閉包」的相關知識，這是 JavaScript 的一個重要觀念，會用到我們之前學到的所有概念，包含一級函式、執行堆、執行環境等等。",
  "source": "@site/docs/functions-extras/closure.mdx",
  "sourceDirName": "functions-extras",
  "slug": "/functions-extras/closure",
  "permalink": "/functions-extras/closure",
  "editUrl": "https://github.com/facebook/docusaurus/tree/main/packages/create-docusaurus/templates/shared/docs/functions-extras/closure.mdx",
  "tags": [],
  "version": "current",
  "sidebarPosition": 1,
  "frontMatter": {
    "sidebar_position": 1
  },
  "sidebar": "tutorialSidebar",
  "previous": {
    "title": "立即呼叫的函式表達式 (IIFEs) 與安全程式碼",
    "permalink": "/objects-and-functions/iife-safe-code"
  },
  "next": {
    "title": "函式工廠 (Function Factory)",
    "permalink": "/functions-extras/function-factory"
  }
}